{
	"configurations" : 
	[
		{
			"directories" : 
			[
				{
					"build" : ".",
					"childIndexes" : 
					[
						1
					],
					"minimumCMakeVersion" : 
					{
						"string" : "3.0"
					},
					"projectIndex" : 0,
					"source" : "."
				},
				{
					"build" : "src",
					"minimumCMakeVersion" : 
					{
						"string" : "3.0"
					},
					"parentIndex" : 0,
					"projectIndex" : 0,
					"source" : "src",
					"targetIndexes" : 
					[
						0
					]
				}
			],
			"name" : "Debug",
			"projects" : 
			[
				{
					"directoryIndexes" : 
					[
						0,
						1
					],
					"name" : "LQR_hopper",
					"targetIndexes" : 
					[
						0
					]
				}
			],
			"targets" : 
			[
				{
					"directoryIndex" : 1,
					"id" : "LQR_hopper::@145eef247bfb46b6828c",
					"jsonFile" : "target-LQR_hopper-Debug-ebad922bac1c7cca8b02.json",
					"name" : "LQR_hopper",
					"projectIndex" : 0
				}
			]
		}
	],
	"kind" : "codemodel",
	"paths" : 
	{
		"build" : "/home/sofia/mujoco_LQR/build",
		"source" : "/home/sofia/mujoco_LQR"
	},
	"version" : 
	{
		"major" : 2,
		"minor" : 0
	}
}
